examples/basic_example.py
examples/multimodal_example.py
examples/multimodal_results/analysis_summary.txt
parismc/__init__.py
parismc/clustering.py
parismc/optimization.py
parismc/sampler.py
parismc/utils.py
parismc-0.1.0.dist-info/licenses/LICENSE
parismc-0.1.0.dist-info/METADATA
parismc-0.1.0.dist-info/WHEEL
parismc-0.1.0.dist-info/top_level.txt
parismc-0.1.0.dist-info/RECORD
