Metadata-Version: 2.4
Name: parismc
Version: 0.1.0
Summary: PARIS: Parallel Adaptive Reweighting Importance Sampling for high-dimensional multi-modal Bayesian inference
Home-page: https://github.com/mx-Liu123/parismc
Author: Alvin J. K. Chua
Author-email: Miaoxin Liu <mx.liu123@outlook.com>
License: MIT
Project-URL: Homepage, https://github.com/mx-Liu123/parismc
Project-URL: Repository, https://github.com/mx-Liu123/parismc
Project-URL: Documentation, https://github.com/mx-Liu123/parismc/blob/main/README.md
Project-URL: Bug Reports, https://github.com/mx-Liu123/parismc/issues
Keywords: monte carlo,bayesian inference,importance sampling,multimodal,adaptive sampling,MCMC
Classifier: Development Status :: 4 - Beta
Classifier: Intended Audience :: Science/Research
Classifier: Intended Audience :: Developers
Classifier: Topic :: Scientific/Engineering :: Mathematics
Classifier: Topic :: Scientific/Engineering :: Physics
Classifier: Topic :: Scientific/Engineering :: Information Analysis
Classifier: License :: OSI Approved :: MIT License
Classifier: Programming Language :: Python :: 3
Classifier: Programming Language :: Python :: 3.8
Classifier: Programming Language :: Python :: 3.9
Classifier: Programming Language :: Python :: 3.10
Classifier: Programming Language :: Python :: 3.11
Classifier: Programming Language :: Python :: 3.12
Classifier: Operating System :: OS Independent
Requires-Python: >=3.8
License-File: LICENSE
Requires-Dist: numpy>=1.20.0
Requires-Dist: scipy>=1.7.0
Requires-Dist: scikit-learn>=1.0.0
Requires-Dist: smt>=2.0.0
Requires-Dist: tqdm>=4.62.0
Provides-Extra: dev
Requires-Dist: pytest>=6.0; extra == "dev"
Requires-Dist: pytest-cov>=2.0; extra == "dev"
Requires-Dist: black>=22.0; extra == "dev"
Requires-Dist: flake8>=4.0; extra == "dev"
Requires-Dist: isort>=5.0; extra == "dev"
Provides-Extra: plotting
Requires-Dist: matplotlib>=3.5.0; extra == "plotting"
Requires-Dist: seaborn>=0.11.0; extra == "plotting"
Provides-Extra: notebook
Requires-Dist: jupyter>=1.0.0; extra == "notebook"
Requires-Dist: ipython>=7.0.0; extra == "notebook"
Provides-Extra: full
Requires-Dist: matplotlib>=3.5.0; extra == "full"
Requires-Dist: seaborn>=0.11.0; extra == "full"
Requires-Dist: jupyter>=1.0.0; extra == "full"
Requires-Dist: ipython>=7.0.0; extra == "full"
Dynamic: home-page
Dynamic: license-file
Dynamic: requires-python
